{
    "boxShadow": "{{appsmith.theme.boxShadow.appBoxShadow}}",
    "borderColor": "#E0DEDE",
    "isVisibleDownload": false,
    "iconSVG": "/static/media/icon.e6911f8bb94dc6c4a102a74740c41763.svg",
    "topRow": 31,
    "isSortable": true,
    "type": "TABLE_WIDGET_V2",
    "inlineEditingSaveOption": "ROW_LEVEL",
    "animateLoading": true,
    "dynamicBindingPathList": [
        {"key": "accentColor"},
        {"key": "borderRadius"},
        {"key": "boxShadow"},
        {"key": "tableData"},
        {"key": "primaryColumns.Cuenta.computedValue"},
        {"key": "primaryColumns.ProductoTipo.computedValue"},
        {"key": "primaryColumns.ProductoDesc.computedValue"},
        {"key": "primaryColumns.DiasMora.computedValue"},
        {"key": "primaryColumns.Moneda.computedValue"},
        {"key": "primaryColumns.DeudaTotal.computedValue"},
        {"key": "primaryColumns.NumeroProducto.computedValue"},
        {"key": "primaryColumns.IdOperacion.computedValue"}
    ],
    "needsHeightForContent": true,
    "leftColumn": 1,
    "delimiter": ",",
    "defaultSelectedRowIndex": 0,
    "accentColor": "{{appsmith.theme.colors.primaryColor}}",
    "isVisibleFilters": true,
    "isVisible": true,
    "enableClientSideSearch": true,
    "version": 2,
    "totalRecordsCount": 0,
    "tags": [
        "Suggested",
        "Display"
    ],
    "isLoading": false,
    "childStylesheet": {
        "button": {
            "boxShadow": "none",
            "borderRadius": "{{appsmith.theme.borderRadius.appBorderRadius}}",
            "buttonColor": "{{appsmith.theme.colors.primaryColor}}"
        },
        "iconButton": {
            "boxShadow": "none",
            "borderRadius": "{{appsmith.theme.borderRadius.appBorderRadius}}",
            "buttonColor": "{{appsmith.theme.colors.primaryColor}}"
        },
        "menuButton": {
            "boxShadow": "none",
            "borderRadius": "{{appsmith.theme.borderRadius.appBorderRadius}}",
            "menuColor": "{{appsmith.theme.colors.primaryColor}}"
        },
        "editActions": {
            "saveButtonColor": "{{appsmith.theme.colors.primaryColor}}",
            "saveBorderRadius": "{{appsmith.theme.borderRadius.appBorderRadius}}",
            "discardBorderRadius": "{{appsmith.theme.borderRadius.appBorderRadius}}",
            "discardButtonColor": "{{appsmith.theme.colors.primaryColor}}"
        }
    },
    "borderRadius": "{{appsmith.theme.borderRadius.appBorderRadius}}",
    "columnUpdatedAt": 1709922267558,
    "originalBottomRow": 47,
    "defaultSelectedRowIndices": [0],
    "mobileBottomRow": 68,
    "widgetName": "Table1",
    "defaultPageSize": 0,
    "columnOrder": [
        "IdOperacion",
        "Cuenta",
        "NumeroProducto",
        "ProductoTipo",
        "DiasMora",
        "Moneda",
        "ProductoDesc",
        "DeudaTotal"
    ],
    "dynamicPropertyPathList": [],
    "displayName": "Table",
    "bottomRow": 47,
    "columnWidthMap": {"ProductoTipo": 151},
    "parentRowSpace": 10,
    "hideCard": false,
    "mobileRightColumn": 21,
    "parentColumnSpace": 17.9375,
    "dynamicTriggerPathList": [],
    "borderWidth": "1",
    "primaryColumns": {
        "IdOperacion": {
            "computedValue": "{{Table1.processedTableData.map((currentRow, currentIndex) => ( currentRow[\"IdOperacion\"]))}}",
            "isEditable": false,
            "alias": "IdOperacion",
            "enableSort": true,
            "isSaveVisible": true,
            "id": "IdOperacion",
            "isDisabled": false,
            "allowSameOptionsInNewRow": true,
            "validation": {},
            "isCellVisible": true,
            "isDerived": false,
            "textSize": "0.875rem",
            "allowCellWrapping": false,
            "index": 0,
            "isDiscardVisible": true,
            "isVisible": false,
            "label": "IdOperacion",
            "fontStyle": "",
            "textColor": "",
            "columnType": "number",
            "horizontalAlignment": "LEFT",
            "isCellEditable": false,
            "width": 150,
            "enableFilter": true,
            "sticky": "",
            "originalId": "IdOperacion",
            "cellBackground": "",
            "verticalAlignment": "CENTER"
        },
        "Moneda": {
            "computedValue": "{{Table1.processedTableData.map((currentRow, currentIndex) => ( currentRow[\"Moneda\"]))}}",
            "isEditable": false,
            "alias": "Moneda",
            "enableSort": true,
            "isSaveVisible": true,
            "id": "Moneda",
            "isDisabled": false,
            "allowSameOptionsInNewRow": true,
            "validation": {},
            "isCellVisible": true,
            "isDerived": false,
            "textSize": "0.875rem",
            "allowCellWrapping": false,
            "index": 4,
            "isDiscardVisible": true,
            "isVisible": true,
            "label": "Moneda",
            "fontStyle": "",
            "textColor": "",
            "columnType": "text",
            "horizontalAlignment": "LEFT",
            "isCellEditable": false,
            "width": 150,
            "enableFilter": true,
            "sticky": "",
            "originalId": "Moneda",
            "cellBackground": "",
            "verticalAlignment": "CENTER"
        },
        "ProductoTipo": {
            "computedValue": "{{Table1.processedTableData.map((currentRow, currentIndex) => ( currentRow[\"ProductoTipo\"]))}}",
            "isEditable": false,
            "alias": "ProductoTipo",
            "enableSort": true,
            "isSaveVisible": true,
            "id": "ProductoTipo",
            "isDisabled": false,
            "allowSameOptionsInNewRow": true,
            "validation": {},
            "isCellVisible": true,
            "isDerived": false,
            "textSize": "0.875rem",
            "allowCellWrapping": false,
            "index": 1,
            "isDiscardVisible": true,
            "isVisible": true,
            "label": "Producto",
            "fontStyle": "",
            "textColor": "",
            "columnType": "text",
            "horizontalAlignment": "LEFT",
            "isCellEditable": false,
            "width": 150,
            "enableFilter": true,
            "sticky": "",
            "originalId": "ProductoTipo",
            "cellBackground": "",
            "verticalAlignment": "CENTER"
        },
        "DiasMora": {
            "computedValue": "{{Table1.processedTableData.map((currentRow, currentIndex) => ( currentRow[\"DiasMora\"]))}}",
            "isEditable": false,
            "alias": "DiasMora",
            "enableSort": true,
            "isSaveVisible": true,
            "id": "DiasMora",
            "isDisabled": false,
            "allowSameOptionsInNewRow": true,
            "validation": {},
            "isCellVisible": true,
            "isDerived": false,
            "textSize": "0.875rem",
            "allowCellWrapping": false,
            "index": 3,
            "isDiscardVisible": true,
            "isVisible": true,
            "label": "Dias de Mora",
            "fontStyle": "",
            "textColor": "",
            "columnType": "number",
            "horizontalAlignment": "LEFT",
            "isCellEditable": false,
            "width": 150,
            "enableFilter": true,
            "sticky": "",
            "originalId": "DiasMora",
            "cellBackground": "",
            "verticalAlignment": "CENTER"
        },
        "NumeroProducto": {
            "computedValue": "{{Table1.processedTableData.map((currentRow, currentIndex) => ( currentRow[\"NumeroProducto\"]))}}",
            "isEditable": false,
            "alias": "NumeroProducto",
            "enableSort": true,
            "isSaveVisible": true,
            "id": "NumeroProducto",
            "isDisabled": false,
            "allowSameOptionsInNewRow": true,
            "validation": {},
            "isCellVisible": true,
            "isDerived": false,
            "textSize": "0.875rem",
            "allowCellWrapping": false,
            "index": 6,
            "isDiscardVisible": true,
            "isVisible": true,
            "label": "NumeroProducto",
            "fontStyle": "",
            "textColor": "",
            "columnType": "text",
            "horizontalAlignment": "LEFT",
            "isCellEditable": false,
            "width": 150,
            "enableFilter": true,
            "sticky": "",
            "originalId": "NumeroProducto",
            "cellBackground": "",
            "verticalAlignment": "CENTER"
        },
        "DeudaTotal": {
            "computedValue": "{{Table1.processedTableData.map((currentRow, currentIndex) => ( currentRow[\"DeudaTotal\"]))}}",
            "isEditable": false,
            "alias": "DeudaTotal",
            "enableSort": true,
            "isSaveVisible": true,
            "id": "DeudaTotal",
            "isDisabled": false,
            "allowSameOptionsInNewRow": true,
            "validation": {},
            "isCellVisible": true,
            "isDerived": false,
            "textSize": "0.875rem",
            "allowCellWrapping": false,
            "index": 5,
            "isDiscardVisible": true,
            "isVisible": true,
            "label": "Deuda Total",
            "fontStyle": "",
            "textColor": "",
            "columnType": "number",
            "horizontalAlignment": "LEFT",
            "isCellEditable": false,
            "width": 150,
            "enableFilter": true,
            "sticky": "",
            "originalId": "DeudaTotal",
            "cellBackground": "",
            "verticalAlignment": "CENTER"
        },
        "Cuenta": {
            "computedValue": "{{Table1.processedTableData.map((currentRow, currentIndex) => ( currentRow[\"Cuenta\"]))}}",
            "isEditable": false,
            "alias": "Cuenta",
            "enableSort": true,
            "isSaveVisible": true,
            "id": "Cuenta",
            "isDisabled": false,
            "allowSameOptionsInNewRow": true,
            "validation": {},
            "isCellVisible": true,
            "isDerived": false,
            "textSize": "0.875rem",
            "allowCellWrapping": false,
            "index": 0,
            "isDiscardVisible": true,
            "isVisible": true,
            "label": "Cuenta",
            "fontStyle": "",
            "textColor": "",
            "columnType": "text",
            "horizontalAlignment": "LEFT",
            "isCellEditable": false,
            "width": 150,
            "enableFilter": true,
            "sticky": "",
            "originalId": "Cuenta",
            "cellBackground": "",
            "verticalAlignment": "CENTER"
        },
        "ProductoDesc": {
            "computedValue": "{{Table1.processedTableData.map((currentRow, currentIndex) => ( currentRow[\"ProductoDesc\"]))}}",
            "isEditable": false,
            "alias": "ProductoDesc",
            "enableSort": true,
            "isSaveVisible": true,
            "id": "ProductoDesc",
            "isDisabled": false,
            "allowSameOptionsInNewRow": true,
            "validation": {},
            "isCellVisible": true,
            "isDerived": false,
            "textSize": "0.875rem",
            "allowCellWrapping": false,
            "index": 2,
            "isDiscardVisible": true,
            "isVisible": true,
            "label": "Tipo",
            "fontStyle": "",
            "textColor": "",
            "columnType": "text",
            "horizontalAlignment": "LEFT",
            "isCellEditable": false,
            "width": 150,
            "enableFilter": true,
            "sticky": "",
            "originalId": "ProductoDesc",
            "cellBackground": "",
            "verticalAlignment": "CENTER"
        }
    },
    "onRowSelected": "",
    "key": "jwt0detm9o",
    "canFreezeColumn": true,
    "isDeprecated": false,
    "rightColumn": 64,
    "textSize": "0.875rem",
    "widgetId": "v605z44gje",
    "minWidth": 450,
    "tableData": "{{TablaProductos.data}}",
    "label": "Data",
    "searchKey": "",
    "parentId": "0",
    "renderMode": "CANVAS",
    "mobileTopRow": 40,
    "horizontalAlignment": "LEFT",
    "isVisibleSearch": true,
    "responsiveBehavior": "fill",
    "originalTopRow": 31,
    "mobileLeftColumn": 0,
    "isVisiblePagination": true,
    "verticalAlignment": "CENTER"
}